vision/__init__.py
vision/vision.py
vision/package/__init__.py
vision/package/common.py
vision/package/roblang.py
vision/package/socketfunc.py
vision/package/visionfunc.py
kais_kit_vision_01-0.0.1.dist-info/METADATA
kais_kit_vision_01-0.0.1.dist-info/WHEEL
kais_kit_vision_01-0.0.1.dist-info/top_level.txt
kais_kit_vision_01-0.0.1.dist-info/RECORD
